yitool/__init__.py
yitool/__main__.py
yitool/cli.py
yitool/const.py
yitool/enums.py
yitool/exceptions.py
yitool/yi_singleton.py
yitool/log/__init__.py
yitool/log/config.py
yitool/log/context.py
yitool/log/core.py
yitool/log/decorators.py
yitool/log/formatters.py
yitool/log/handlers.py
yitool/misc/__init__.py
yitool/misc/file_modified.py
yitool/misc/job_store.py
yitool/shared/__init__.py
yitool/shared/cron.py
yitool/shared/kv_storage.py
yitool/shared/modified.py
yitool/shared/pubsub.py
yitool/shared/stack.py
yitool/shared/subscriber.py
yitool/utils/__init__.py
yitool/utils/_humps.py
yitool/utils/arr_utils.py
yitool/utils/class_utils.py
yitool/utils/compress_utils.py
yitool/utils/config_utils.py
yitool/utils/convert_utils.py
yitool/utils/crypto_utils.py
yitool/utils/date_utils.py
yitool/utils/dict_utils.py
yitool/utils/env_utils.py
yitool/utils/file_utils.py
yitool/utils/fun_utils.py
yitool/utils/id_utils.py
yitool/utils/json_utils.py
yitool/utils/path_utils.py
yitool/utils/random_utils.py
yitool/utils/security_utils.py
yitool/utils/str_utils.py
yitool/utils/system_utils.py
yitool/utils/url_utils.py
yitool/utils/validator_utils.py
yitool/utils/yaml_utils.py
yitool/yi_cache/__init__.py
yitool/yi_cache/_abc.py
yitool/yi_cache/yi_cache_memory.py
yitool/yi_cache/yi_cache_redis.py
yitool/yi_cache/yi_cache_ttl.py
yitool/yi_cache/yi_redis.py
yitool/yi_celery/__init__.py
yitool/yi_celery/email_tasks.py
yitool/yi_celery/router.py
yitool/yi_celery/yi_celery.py
yitool/yi_config/__init__.py
yitool/yi_config/api_key.py
yitool/yi_config/app.py
yitool/yi_config/celery.py
yitool/yi_config/cors.py
yitool/yi_config/database.py
yitool/yi_config/datasource.py
yitool/yi_config/jwt.py
yitool/yi_config/middleware.py
yitool/yi_config/server.py
yitool/yi_config/yi_config.py
yitool/yi_db/__init__.py
yitool/yi_db/_abc.py
yitool/yi_db/base.py
yitool/yi_db/engine.py
yitool/yi_db/mixin.py
yitool/yi_db/session.py
yitool/yi_db/yi_db.py
yitool/yi_db/yi_db_sqlalchemy.py
yitool-0.6.0.dist-info/licenses/LICENSE
yitool-0.6.0.dist-info/METADATA
yitool-0.6.0.dist-info/WHEEL
yitool-0.6.0.dist-info/entry_points.txt
yitool-0.6.0.dist-info/top_level.txt
yitool-0.6.0.dist-info/RECORD
