Metadata-Version: 2.4
Name: yitool
Version: 0.6.0
Summary: @yitech/yitool 工具包
Author-email: Tony Chen <chruit@outlook.com>
Project-URL: Homepage, https://gitee.com/yi_tech/yitool
Project-URL: Repository, https://gitee.com/yi_tech/yitool
Requires-Python: >=3.12
License-File: LICENSE
Requires-Dist: cachetools>=6.2.0
Requires-Dist: celery>=5.4.0
Requires-Dist: click>=8.1.0
Requires-Dist: croniter>=6.0.0
Requires-Dist: deepmerge>=2.0
Requires-Dist: limits>=3.11.0
Requires-Dist: pydantic>=2.11.9
Requires-Dist: pydantic-settings>=2.12.0
Requires-Dist: pydantic-extra-types>=2.11.0
Requires-Dist: python-dotenv>=1.1.1
Requires-Dist: pyyaml>=6.0.3
Requires-Dist: rich>=14.2.0
Requires-Dist: setuptools>=80.9.0
Requires-Dist: psutil>=7.1.0
Requires-Dist: tornado>=6.5.4
Requires-Dist: pymysql>=1.1.2
Requires-Dist: sqlalchemy>=2.0.45
Requires-Dist: sqlmodel>=0.0.21
Requires-Dist: redis>=6.4.0
Requires-Dist: fastapi[standard]>=0.128.0
Requires-Dist: msgpack>=1.1.2
Requires-Dist: blinker>=1.9.0
Requires-Dist: aiosqlite>=0.22.1
Requires-Dist: cryptography>=46.0.3
Requires-Dist: python-jose>=3.5.0
Requires-Dist: python-multipart>=0.0.21
Requires-Dist: markdown-it-py>=4.0.0
Requires-Dist: passlib>=1.7.4
Requires-Dist: prometheus-client>=0.20.0
Requires-Dist: asyncmy>=0.2.11
Dynamic: license-file
